tinyquant/__init__.py
tinyquant-0.1.0.dist-info/METADATA
tinyquant-0.1.0.dist-info/WHEEL
tinyquant-0.1.0.dist-info/licenses/LICENSE
tinyquant-0.1.0.dist-info/RECORD
